bunker_stats_rs-0.2.9.dist-info/METADATA
bunker_stats_rs-0.2.9.dist-info/WHEEL
bunker_stats_rs-0.2.9.dist-info/licenses/LICENSE
bunker_stats_rs/__init__.py
bunker_stats_rs/bunker_stats_rs.cp310-win_amd64.pyd
bunker_stats_rs-0.2.9.dist-info/RECORD
