Metadata-Version: 2.4
Name: bunker-stats-rs
Version: 0.2.9
Classifier: Programming Language :: Rust
Classifier: Programming Language :: Python
Classifier: Programming Language :: Python :: 3
Classifier: Programming Language :: Python :: 3 :: Only
Classifier: Programming Language :: Python :: 3.8
Classifier: Programming Language :: Python :: 3.9
Classifier: Programming Language :: Python :: 3.10
Classifier: Programming Language :: Python :: 3.11
Classifier: Programming Language :: Python :: 3.12
Classifier: Operating System :: OS Independent
Classifier: Development Status :: 3 - Alpha
Classifier: Intended Audience :: Developers
Classifier: Intended Audience :: Science/Research
Classifier: Intended Audience :: Financial and Insurance Industry
Classifier: License :: OSI Approved :: MIT License
Classifier: Topic :: Scientific/Engineering
Classifier: Topic :: Scientific/Engineering :: Information Analysis
Classifier: Topic :: Software Development :: Libraries
Classifier: Topic :: Software Development :: Libraries :: Python Modules
Classifier: Topic :: Utilities
Requires-Dist: numpy>=1.22
License-File: LICENSE
Summary: Ultra-fast Rust-powered statistics and time-series utilities for Python.
Author-email: Adam Ezzat <adamezzat24@gmail.com>
Requires-Python: >=3.8
Project-URL: homepage, https://github.com/AdamEzzat1/bunker-stats
Project-URL: repository, https://github.com/AdamEzzat1/bunker-stats
Project-URL: documentation, https://github.com/AdamEzzat1/bunker-stats
Project-URL: issues, https://github.com/AdamEzzat1/bunker-stats/issues
